{
    "homepage": "https://github.com/Locietta/xanmod-kernel-WSL2",
    "license": "MIT",
    "extract_dir": "",
    "bin": "",
    "post_install": [
        "#########################################",
        "# set `.wslconfig` to use custom kernel #",
        "#########################################",
        "$ini = Add-Type -memberDefinition @\"",
        "[DllImport(\"Kernel32\")]",
        "public static extern long WritePrivateProfileString (string section, string key, string val, string filePath);",
        "[DllImport(\"Kernel32\")]",
        "public static extern int GetPrivateProfileString (string section, string key, string def, StringBuilder retVal, int size, string filePath);",
        "\"@ -passthru -name MyPrivateProfileString -UsingNamespace System.Text",
        "$kernel_path=\"$dir\\bzImage\" -replace \"\\\\\", \"\\\\\" # double all back-slashess",
        "$null = $ini::WritePrivateProfileString(\"wsl2\", \"kernel\", $kernel_path, \"$env:USERPROFILE\\.wslconfig\")"
    ],
    "post_uninstall": [
        "##########################################",
        "# recover `.wslconfig` to default kernel #",
        "##########################################",
        "$ini = Add-Type -memberDefinition @\"",
        "[DllImport(\"Kernel32\")]",
        "public static extern long WritePrivateProfileString (string section,string key, string val, string filePath);",
        "[DllImport(\"Kernel32\")]",
        "public static extern int GetPrivateProfileString (string section, string key, string def, StringBuilder retVal, int size, string filePath);",
        "\"@ -passthru -name MyPrivateProfileString -UsingNamespace System.Text",
        "$null = $ini::WritePrivateProfileString(\"wsl2\", \"kernel\", $null, \"$env:USERPROFILE\\.wslconfig\")"
    ],
    "version": "5.19.3-1",
    "url": "https://github.com/Locietta/xanmod-kernel-WSL2/releases/download/5.19.3-xanmod1-locietta-WSL2/bzImage",
    "hash": "7967bb2daa57aeab1869d603f26b94f8b0893074a9453e43a2a2ef343c651006",
    "checkver": {
        "github": "https://github.com/Locietta/xanmod-kernel-WSL2",
        "regex": "(?<main>[\\d.]+)-xanmod(?<xanmod>[\\d]+)-locietta-WSL2",
        "replace": "${1}-${2}"
    },
    "autoupdate": {
        "url": "https://github.com/Locietta/xanmod-kernel-WSL2/releases/download/$matchMain-xanmod$matchXanmod-locietta-WSL2/bzImage",
        "hash": {
            "url": "https://github.com/Locietta/xanmod-kernel-WSL2/releases/download/$matchMain-xanmod$matchXanmod-locietta-WSL2/bzImage.sha256"
        }
    }
}
